Metadata-Version: 2.0
Name: django-make-app
Version: 0.1.3
Summary: Define models and fields using YAML and generate app for Django with views, forms, templates etc.
Home-page: https://github.com/illagrenan/django-make-app
Author: Vasek Dohnal
Author-email: vaclav.dohnal@gmail.com
License: MIT
Platform: UNKNOWN
Classifier: Development Status :: 2 - Pre-Alpha
Classifier: Framework :: Django
Classifier: Intended Audience :: Developers
Classifier: Environment :: Console
Classifier: License :: OSI Approved :: MIT License
Classifier: Natural Language :: English
Classifier: Programming Language :: Python :: 2
Classifier: Programming Language :: Python :: 2.7
Classifier: Programming Language :: Python :: 3
Classifier: Programming Language :: Python :: 3.3
Classifier: Programming Language :: Python :: 3.4
Classifier: Programming Language :: Python :: 3.5
Classifier: Programming Language :: Python :: 3.6
Classifier: Operating System :: OS Independent
Classifier: Programming Language :: Python :: Implementation :: CPython
Classifier: Programming Language :: Python :: Implementation :: PyPy
Requires-Dist: click
Requires-Dist: glob2
Requires-Dist: isort
Requires-Dist: jinja2
Requires-Dist: pyaml
Requires-Dist: yapf
